{"map_name": "de_poseidon", "nodes": [{"id": 0, "x": -377.5, "y": 593.9998, "z": -44.2033, "corner": false}, {"id": 2, "x": -148.96, "y": 732.83, "z": -44.2033, "corner": false}, {"id": 4, "x": 1120.9999, "y": -1053.7502, "z": 5.1301, "corner": false}, {"id": 5, "x": -248.0, "y": -164.5002, "z": -68.2033, "corner": false}, {"id": 6, "x": 1183.9999, "y": -1171.7502, "z": 5.1301, "corner": false}, {"id": 7, "x": 447.0, "y": 487.9998, "z": 3.1301, "corner": false}, {"id": 9, "x": 1209.9999, "y": -877.0002, "z": 4.099, "corner": false}, {"id": 10, "x": 1352.12, "y": 362.98, "z": 131.7967, "corner": false, "action": "jump"}, {"id": 11, "x": -443.0, "y": 427.87, "z": -44.2033, "corner": false}, {"id": 12, "x": 616.4999, "y": -1640.5002, "z": -44.2033, "corner": false}, {"id": 13, "x": 698.55, "y": -1787.51, "z": -42.8699, "corner": false}, {"id": 14, "x": 360.5, "y": 625.7498, "z": 3.7968, "corner": false}, {"id": 15, "x": 1213.0, "y": 653.9998, "z": 34.4634, "corner": false}, {"id": 19, "x": 746.9999, "y": -1681.0001, "z": -44.2033, "corner": false}, {"id": 21, "x": 511.0, "y": 237.9999, "z": 3.1301, "corner": false}, {"id": 22, "x": 570.4999, "y": 7.9999, "z": 5.1301, "corner": false}, {"id": 23, "x": -343.88, "y": 47.17, "z": -68.2033, "corner": false}, {"id": 24, "x": 543.9999, "y": 107.9999, "z": 3.7968, "corner": false}, {"id": 25, "x": 415.9999, "y": 39.9999, "z": 3.7968, "corner": false}, {"id": 26, "x": 352.0, "y": 103.9999, "z": 3.7968, "corner": false}, {"id": 29, "x": 918.9999, "y": -616.0002, "z": 3.7968, "corner": false, "action": "shift"}, {"id": 31, "x": 777.0, "y": 2.4999, "z": 6.4634, "corner": false}, {"id": 32, "x": 162.5, "y": -544.0002, "z": 3.7968, "corner": false}, {"id": 33, "x": 213.0, "y": 30.9999, "z": 3.7968, "corner": false}, {"id": 35, "x": -214.41, "y": -829.07, "z": 3.7968, "corner": false}, {"id": 36, "x": 264.5, "y": 689.7498, "z": 3.7968, "corner": false}, {"id": 37, "x": 846.9999, "y": -1664.5002, "z": -44.2033, "corner": false}, {"id": 38, "x": 406.0, "y": -398.0002, "z": 5.1301, "corner": false}, {"id": 41, "x": 427.0, "y": -290.5002, "z": 6.4634, "corner": false, "action": "shift"}, {"id": 42, "x": 32.0, "y": 767.4998, "z": -41.5366, "corner": false}, {"id": 43, "x": 1145.5, "y": 725.4998, "z": 33.7967, "corner": false}, {"id": 46, "x": 1144.9999, "y": -589.0235, "z": 4.1301, "corner": false}, {"id": 49, "x": 858.9999, "y": -106.0001, "z": 7.7968, "corner": false}, {"id": 50, "x": 64.0, "y": 668.4998, "z": -38.8699, "corner": false}, {"id": 51, "x": 534.4999, "y": -497.5002, "z": 6.4634, "corner": false}, {"id": 52, "x": -4.96, "y": -692.34, "z": 3.7968, "corner": false}, {"id": 53, "x": 849.0, "y": -1787.0, "z": -43.5366, "corner": true}, {"id": 54, "x": 384.0, "y": 263.9999, "z": -2.2033, "corner": false}, {"id": 55, "x": 788.5, "y": -357.0002, "z": 7.7968, "corner": false}, {"id": 56, "x": -21.23, "y": -543.17, "z": 3.1301, "corner": false}, {"id": 57, "x": 1517.6, "y": -9.46, "z": 131.7967, "corner": false, "action": "shift"}, {"id": 58, "x": -466.61, "y": 305.19, "z": -49.5366, "corner": false}, {"id": 63, "x": 970.9999, "y": -1603.5004, "z": -38.8699, "corner": false}, {"id": 66, "x": 194.5, "y": -66.5001, "z": 3.7968, "corner": false}, {"id": 67, "x": 363.0, "y": -141.5002, "z": 5.1301, "corner": false, "action": "shift"}, {"id": 68, "x": -88.0, "y": -124.5002, "z": -68.2033, "corner": false}, {"id": 69, "x": -10.0, "y": -1244.0003, "z": -28.2032, "corner": false}, {"id": 72, "x": 189.5, "y": -638.5002, "z": 3.7968, "corner": false}, {"id": 74, "x": 439.5, "y": -61.5001, "z": 5.1301, "corner": false}, {"id": 79, "x": 817.4999, "y": 274.9999, "z": 131.7967, "corner": true}, {"id": 80, "x": 737.4999, "y": -475.0002, "z": 7.7968, "corner": false}, {"id": 81, "x": 352.0, "y": 455.9998, "z": 3.1301, "corner": false}, {"id": 82, "x": 319.5, "y": -519.5002, "z": 3.7968, "corner": false, "action": "shift"}, {"id": 84, "x": 964.5, "y": 140.9999, "z": 3.7968, "corner": false}, {"id": 85, "x": 1177.4999, "y": 1016.4998, "z": 43.7968, "corner": false}, {"id": 86, "x": 124.37, "y": -1507.29, "z": -38.8699, "corner": false}, {"id": 87, "x": -63.0, "y": -1069.5002, "z": -28.2032, "corner": true, "action": "crouch"}, {"id": 88, "x": 1128.4999, "y": 280.4999, "z": 131.7967, "corner": false, "action": "shift"}, {"id": 89, "x": 497.13, "y": 356.95, "z": -0.8699, "corner": false}, {"id": 91, "x": 380.0, "y": -1588.5004, "z": -44.2033, "corner": false}, {"id": 92, "x": 541.9999, "y": 429.9999, "z": 3.1301, "corner": false}, {"id": 93, "x": 555.4999, "y": -628.0002, "z": 3.7968, "corner": false}, {"id": 94, "x": 1288.68, "y": -916.43, "z": 4.099, "corner": false}, {"id": 95, "x": 577.9999, "y": 771.4998, "z": 18.4634, "corner": false}, {"id": 97, "x": 1426.66, "y": 278.0, "z": 131.7967, "corner": false, "action": "crouch"}, {"id": 101, "x": 264.5, "y": -116.0002, "z": 3.7968, "corner": false, "action": "shift"}, {"id": 102, "x": 554.4999, "y": -1789.5, "z": -43.5366, "corner": false}, {"id": 103, "x": 827.5, "y": -1213.5002, "z": 4.4634, "corner": false}, {"id": 105, "x": 115.41, "y": 78.3, "z": 3.7968, "corner": false, "action": "jump"}, {"id": 106, "x": 1307.58, "y": 101.64, "z": 3.7968, "corner": false}, {"id": 107, "x": 917.5, "y": -478.5002, "z": 6.4634, "corner": false}, {"id": 109, "x": 1092.4999, "y": -471.0002, "z": 4.4634, "corner": false}, {"id": 110, "x": 362.5, "y": 820.9998, "z": 4.4634, "corner": false}, {"id": 111, "x": 630.4999, "y": -432.5002, "z": 7.7968, "corner": false}, {"id": 112, "x": -151.75, "y": -245.7502, "z": -61.5366, "corner": false}, {"id": 113, "x": 749.0, "y": -279.5002, "z": 7.7968, "corner": false}, {"id": 115, "x": 1102.9999, "y": -663.0235, "z": 4.1301, "corner": false}, {"id": 116, "x": 622.42, "y": -1009.66, "z": 3.7968, "corner": false}, {"id": 117, "x": 1033.4999, "y": -1074.5002, "z": 5.1301, "corner": false}, {"id": 118, "x": -44.0, "y": -835.5003, "z": 3.7968, "corner": false}, {"id": 119, "x": 145.0, "y": 699.4998, "z": -14.2033, "corner": false}, {"id": 121, "x": 693.4999, "y": 100.9999, "z": 5.1301, "corner": false}, {"id": 122, "x": 958.9999, "y": -1005.5002, "z": 3.7968, "corner": false}, {"id": 125, "x": -398.0, "y": 799.9998, "z": -44.2033, "corner": false}, {"id": 126, "x": 145.0, "y": 785.9998, "z": -14.2033, "corner": false}, {"id": 127, "x": 1386.49, "y": 427.07, "z": 3.1301, "corner": false}, {"id": 128, "x": 571.68, "y": -884.61, "z": 3.7968, "corner": false}, {"id": 130, "x": 142.0, "y": 214.9999, "z": -1.5366, "corner": false}, {"id": 132, "x": 498.77, "y": -354.58, "z": 7.7968, "corner": false}, {"id": 134, "x": 54.0, "y": -1323.5004, "z": -28.2032, "corner": false}, {"id": 137, "x": 8.0, "y": 281.9999, "z": -23.5366, "corner": false}, {"id": 138, "x": -59.5, "y": -273.7502, "z": -52.8699, "corner": false}, {"id": 139, "x": -59.5, "y": -363.5002, "z": -15.5366, "corner": false}, {"id": 140, "x": -251.11, "y": -1037.08, "z": -23.5366, "corner": false, "action": "shift"}, {"id": 143, "x": -5.5, "y": 180.4999, "z": 43.7968, "corner": true}, {"id": 144, "x": 271.5, "y": -358.5002, "z": 3.7968, "corner": false}, {"id": 145, "x": 17.0, "y": 449.4999, "z": 43.7968, "corner": true}, {"id": 148, "x": 893.0, "y": 1024.9999, "z": 43.7968, "corner": false}, {"id": 149, "x": -179.5, "y": 273.9999, "z": -36.2033, "corner": true}, {"id": 150, "x": 952.9999, "y": -31.0001, "z": 7.7968, "corner": false}, {"id": 153, "x": 1040.23, "y": 894.74, "z": 39.1301, "corner": false}, {"id": 154, "x": 372.34, "y": 353.79, "z": -6.2033, "corner": false}, {"id": 156, "x": 1010.0, "y": -1180.5002, "z": 6.4634, "corner": false}, {"id": 157, "x": 529.4999, "y": -1150.0003, "z": 3.7968, "corner": false}, {"id": 158, "x": 228.92, "y": 369.22, "z": 43.7968, "corner": false, "action": "jump"}, {"id": 159, "x": 49.5, "y": -242.0002, "z": 3.7968, "corner": false}, {"id": 160, "x": 817.55, "y": 739.29, "z": 34.4634, "corner": false}, {"id": 161, "x": 77.5, "y": -90.5001, "z": 3.7968, "corner": false}, {"id": 162, "x": -102.0, "y": 124.4999, "z": -11.5366, "corner": false}, {"id": 163, "x": 477.74, "y": -1604.5, "z": -43.5366, "corner": false}, {"id": 168, "x": -27.0, "y": -192.0002, "z": -68.2033, "corner": false}, {"id": 169, "x": -75.5, "y": 526.9998, "z": -44.2033, "corner": false}, {"id": 170, "x": -245.0, "y": 234.4999, "z": 3.7968, "corner": false, "action": "jump"}, {"id": 171, "x": -235.0, "y": 147.9999, "z": 3.7968, "corner": false, "action": "jump"}, {"id": 172, "x": -192.5, "y": 538.4998, "z": -44.2033, "corner": false}, {"id": 173, "x": 1513.51, "y": -537.13, "z": 131.7967, "corner": false}, {"id": 175, "x": 633.4999, "y": -95.0001, "z": 7.7968, "corner": false}, {"id": 176, "x": 1492.0001, "y": -824.0002, "z": 51.7967, "corner": false}, {"id": 179, "x": 219.0, "y": 517.4999, "z": 43.7968, "corner": true}, {"id": 180, "x": 230.0, "y": -1155.5003, "z": 3.7968, "corner": false}, {"id": 183, "x": -128.25, "y": -326.2502, "z": -33.5366, "corner": false}, {"id": 184, "x": 119.0, "y": 315.9999, "z": -12.8699, "corner": false}, {"id": 186, "x": -201.5, "y": 421.2499, "z": -6.8699, "corner": false}, {"id": 189, "x": 837.4999, "y": 131.4999, "z": 3.7968, "corner": false}, {"id": 190, "x": 1050.56, "y": -1287.79, "z": 3.1301, "corner": false}, {"id": 191, "x": -81.0, "y": 263.4999, "z": -36.2033, "corner": false}, {"id": 192, "x": -110.0, "y": 11.4999, "z": 43.7968, "corner": false}, {"id": 196, "x": 358.0001, "y": -987.0002, "z": 3.7968, "corner": false}, {"id": 198, "x": 1346.39, "y": 546.84, "z": 20.4634, "corner": false, "action": "shift"}, {"id": 200, "x": 818.0, "y": -215.0002, "z": 7.7968, "corner": false}, {"id": 203, "x": 342.5001, "y": -1147.0003, "z": 3.7968, "corner": false}, {"id": 205, "x": 529.4999, "y": 667.7498, "z": 19.1301, "corner": false}, {"id": 207, "x": 186.5, "y": -1047.0003, "z": 3.7968, "corner": false}, {"id": 209, "x": -27.0, "y": -72.0002, "z": -68.2033, "corner": false}, {"id": 210, "x": 782.9999, "y": -1359.0004, "z": 5.7968, "corner": false}, {"id": 213, "x": 933.9999, "y": -176.0001, "z": 7.7968, "corner": false}, {"id": 214, "x": 448.0, "y": -495.5002, "z": 5.1301, "corner": false}, {"id": 215, "x": 275.0, "y": -1073.5002, "z": 37.7967, "corner": false}, {"id": 216, "x": 526.4999, "y": 566.2498, "z": 8.4634, "corner": false}, {"id": 217, "x": 36.5, "y": 88.9999, "z": 43.7968, "corner": false}, {"id": 218, "x": 571.25, "y": -698.06, "z": 3.7968, "corner": false}, {"id": 219, "x": 1261.5, "y": -1209.5002, "z": 3.7968, "corner": false}, {"id": 223, "x": 175.35, "y": 571.54, "z": 3.7968, "corner": true, "action": "jump"}, {"id": 224, "x": -14.0, "y": -459.5002, "z": 3.7968, "corner": false}, {"id": 228, "x": 104.0, "y": 450.9999, "z": 43.7968, "corner": false}, {"id": 230, "x": 38.0, "y": 542.9998, "z": -44.2033, "corner": false}, {"id": 232, "x": 832.28, "y": -1051.47, "z": 3.7968, "corner": false}, {"id": 234, "x": -283.0, "y": 446.4998, "z": -44.2033, "corner": false}, {"id": 235, "x": 880.5, "y": -1150.5002, "z": 3.7968, "corner": false}, {"id": 240, "x": 66.0, "y": -379.0002, "z": 3.7968, "corner": false}, {"id": 241, "x": 679.0, "y": -1484.0004, "z": -44.2033, "corner": true}, {"id": 244, "x": 921.5, "y": -1248.0003, "z": 5.7968, "corner": false}, {"id": 246, "x": -103.03, "y": 386.57, "z": -10.8699, "corner": false, "action": "jump"}, {"id": 248, "x": 1087.15, "y": 122.1, "z": 5.1301, "corner": false}, {"id": 249, "x": 434.5, "y": -1171.0002, "z": 3.7968, "corner": false}, {"id": 253, "x": -31.0, "y": -1154.5002, "z": -28.2032, "corner": false}, {"id": 258, "x": -16.5, "y": -756.5002, "z": 3.7968, "corner": false}, {"id": 259, "x": 41.01, "y": -1051.92, "z": 11.7967, "corner": false}, {"id": 260, "x": 69.5, "y": -1163.0002, "z": -28.2032, "corner": false}, {"id": 264, "x": 269.0, "y": -661.0002, "z": 3.7968, "corner": false}, {"id": 266, "x": -4.0, "y": -612.0002, "z": 3.7968, "corner": false}, {"id": 270, "x": 529.9999, "y": -97.5001, "z": 6.4634, "corner": false}, {"id": 274, "x": 39.5, "y": 7.4999, "z": 43.7968, "corner": false}, {"id": 276, "x": 784.68, "y": -1134.27, "z": 3.7968, "corner": false}, {"id": 279, "x": 606.9999, "y": 177.9999, "z": 3.7968, "corner": false}, {"id": 280, "x": 877.0, "y": -4.0001, "z": 7.7968, "corner": false}, {"id": 281, "x": -184.5, "y": 39.9999, "z": -36.2033, "corner": false}, {"id": 283, "x": 116.0, "y": -1108.0002, "z": 11.7967, "corner": false}, {"id": 286, "x": -34.67, "y": -1630.51, "z": -28.2032, "corner": false}, {"id": 287, "x": 1410.97, "y": -979.91, "z": 4.4634, "corner": false}, {"id": 288, "x": 1036.5, "y": -568.5002, "z": 3.7968, "corner": false}, {"id": 295, "x": -112.73, "y": -1167.12, "z": -28.2032, "corner": false}, {"id": 296, "x": 586.4999, "y": -1208.0002, "z": 3.7968, "corner": false}, {"id": 298, "x": 737.4999, "y": -1225.0003, "z": 3.7968, "corner": false}, {"id": 299, "x": 1384.44, "y": 163.24, "z": 131.7967, "corner": false}, {"id": 300, "x": 954.0, "y": 59.4999, "z": 3.7968, "corner": false}, {"id": 301, "x": 879.9999, "y": -1318.0003, "z": 5.7968, "corner": false}, {"id": 302, "x": 955.62, "y": 739.84, "z": 35.1301, "corner": false}, {"id": 304, "x": 915.0, "y": -1733.0002, "z": -44.2033, "corner": false}, {"id": 307, "x": -7.75, "y": 363.9999, "z": -26.2033, "corner": false}, {"id": 312, "x": -507.99, "y": -177.32, "z": -68.2033, "corner": false}, {"id": 317, "x": 664.9999, "y": -573.0002, "z": 3.7968, "corner": false}, {"id": 318, "x": -125.0, "y": 473.9999, "z": 2.4634, "corner": false}, {"id": 319, "x": 682.7058, "y": -1388.5004, "z": 21.1301, "corner": false}, {"id": 323, "x": 181.0381, "y": -965.8611, "z": 21.7967, "corner": false}, {"id": 324, "x": 1120.7499, "y": -1263.7502, "z": 6.4634, "corner": false}, {"id": 326, "x": 1068.99, "y": 1092.05, "z": 43.7968, "corner": false}, {"id": 331, "x": 1411.47, "y": -41.85, "z": 0.0, "corner": false, "action": ""}, {"id": 332, "x": 1027.18, "y": 796.08, "z": 0.0, "corner": false, "action": ""}, {"id": 333, "x": 1101.34, "y": -1434.16, "z": 0.0, "corner": false, "action": ""}], "edges": [{"from": 0, "to": 11, "weight": 178.5759}, {"from": 11, "to": 0, "weight": 178.5759}, {"from": 2, "to": 42, "weight": 184.2512}, {"from": 42, "to": 2, "weight": 184.2512}, {"from": 2, "to": 169, "weight": 218.5462}, {"from": 169, "to": 2, "weight": 218.5462}, {"from": 4, "to": 6, "weight": 133.7647}, {"from": 6, "to": 4, "weight": 133.7647}, {"from": 4, "to": 9, "weight": 197.8955}, {"from": 9, "to": 4, "weight": 197.8955}, {"from": 4, "to": 117, "weight": 89.9267}, {"from": 117, "to": 4, "weight": 89.9267}, {"from": 5, "to": 68, "weight": 164.9242}, {"from": 68, "to": 5, "weight": 164.9242}, {"from": 5, "to": 112, "weight": 126.1351}, {"from": 112, "to": 5, "weight": 126.1351}, {"from": 6, "to": 324, "weight": 111.6528}, {"from": 324, "to": 6, "weight": 111.6528}, {"from": 7, "to": 81, "weight": 100.2447}, {"from": 81, "to": 7, "weight": 100.2447}, {"from": 7, "to": 92, "weight": 111.3057}, {"from": 92, "to": 7, "weight": 111.3057}, {"from": 9, "to": 94, "weight": 88.0072}, {"from": 94, "to": 9, "weight": 88.0072}, {"from": 10, "to": 88, "weight": 238.3462}, {"from": 88, "to": 10, "weight": 238.3462}, {"from": 10, "to": 97, "weight": 113.039}, {"from": 97, "to": 10, "weight": 113.039}, {"from": 11, "to": 58, "weight": 124.9312}, {"from": 58, "to": 11, "weight": 124.9312}, {"from": 12, "to": 19, "weight": 136.64}, {"from": 19, "to": 12, "weight": 136.64}, {"from": 12, "to": 102, "weight": 161.3858}, {"from": 102, "to": 12, "weight": 161.3858}, {"from": 12, "to": 241, "weight": 168.5184}, {"from": 241, "to": 12, "weight": 168.5184}, {"from": 13, "to": 53, "weight": 150.4509}, {"from": 53, "to": 13, "weight": 150.4509}, {"from": 13, "to": 102, "weight": 144.0638}, {"from": 102, "to": 13, "weight": 144.0638}, {"from": 14, "to": 36, "weight": 115.3776}, {"from": 36, "to": 14, "weight": 115.3776}, {"from": 14, "to": 179, "weight": 182.5932}, {"from": 179, "to": 14, "weight": 182.5932}, {"from": 15, "to": 43, "weight": 98.3308}, {"from": 43, "to": 15, "weight": 98.3308}, {"from": 19, "to": 37, "weight": 101.3521}, {"from": 37, "to": 19, "weight": 101.3521}, {"from": 21, "to": 54, "weight": 129.7438}, {"from": 54, "to": 21, "weight": 129.7438}, {"from": 21, "to": 89, "weight": 119.756}, {"from": 89, "to": 21, "weight": 119.756}, {"from": 21, "to": 279, "weight": 113.2097}, {"from": 279, "to": 21, "weight": 113.2097}, {"from": 22, "to": 24, "weight": 103.4603}, {"from": 24, "to": 22, "weight": 103.4603}, {"from": 22, "to": 175, "weight": 120.7688}, {"from": 175, "to": 22, "weight": 120.7688}, {"from": 22, "to": 270, "weight": 113.0145}, {"from": 270, "to": 22, "weight": 113.0145}, {"from": 24, "to": 25, "weight": 144.9414}, {"from": 25, "to": 24, "weight": 144.9414}, {"from": 24, "to": 279, "weight": 94.1754}, {"from": 279, "to": 24, "weight": 94.1754}, {"from": 25, "to": 26, "weight": 90.5096}, {"from": 26, "to": 25, "weight": 90.5096}, {"from": 25, "to": 74, "weight": 104.1935}, {"from": 74, "to": 25, "weight": 104.1935}, {"from": 26, "to": 33, "weight": 157.0032}, {"from": 33, "to": 26, "weight": 157.0032}, {"from": 26, "to": 54, "weight": 163.2789}, {"from": 54, "to": 26, "weight": 163.2789}, {"from": 29, "to": 115, "weight": 189.9139}, {"from": 115, "to": 29, "weight": 189.9139}, {"from": 29, "to": 288, "weight": 126.738}, {"from": 288, "to": 29, "weight": 126.738}, {"from": 31, "to": 49, "weight": 136.0074}, {"from": 49, "to": 31, "weight": 136.0074}, {"from": 31, "to": 121, "weight": 129.1367}, {"from": 121, "to": 31, "weight": 129.1367}, {"from": 31, "to": 175, "weight": 173.4944}, {"from": 175, "to": 31, "weight": 173.4944}, {"from": 32, "to": 56, "weight": 183.7319}, {"from": 56, "to": 32, "weight": 183.7319}, {"from": 32, "to": 72, "weight": 98.2815}, {"from": 72, "to": 32, "weight": 98.2815}, {"from": 32, "to": 82, "weight": 158.9001}, {"from": 82, "to": 32, "weight": 158.9001}, {"from": 33, "to": 66, "weight": 99.2396}, {"from": 66, "to": 33, "weight": 99.2396}, {"from": 33, "to": 105, "weight": 108.4486}, {"from": 105, "to": 33, "weight": 108.4486}, {"from": 36, "to": 119, "weight": 121.2407}, {"from": 119, "to": 36, "weight": 121.2407}, {"from": 37, "to": 304, "weight": 96.5208}, {"from": 304, "to": 37, "weight": 96.5208}, {"from": 38, "to": 41, "weight": 109.5401}, {"from": 41, "to": 38, "weight": 109.5401}, {"from": 38, "to": 82, "weight": 149.1519}, {"from": 82, "to": 38, "weight": 149.1519}, {"from": 38, "to": 144, "weight": 140.1866}, {"from": 144, "to": 38, "weight": 140.1866}, {"from": 38, "to": 214, "weight": 106.1614}, {"from": 214, "to": 38, "weight": 106.1614}, {"from": 41, "to": 67, "weight": 162.169}, {"from": 67, "to": 41, "weight": 162.169}, {"from": 41, "to": 132, "weight": 96.2141}, {"from": 132, "to": 41, "weight": 96.2141}, {"from": 42, "to": 50, "weight": 104.0774}, {"from": 50, "to": 42, "weight": 104.0774}, {"from": 46, "to": 115, "weight": 85.0882}, {"from": 115, "to": 46, "weight": 85.0882}, {"from": 49, "to": 150, "weight": 120.2539}, {"from": 150, "to": 49, "weight": 120.2539}, {"from": 49, "to": 200, "weight": 116.4561}, {"from": 200, "to": 49, "weight": 116.4561}, {"from": 49, "to": 280, "weight": 103.5761}, {"from": 280, "to": 49, "weight": 103.5761}, {"from": 50, "to": 119, "weight": 90.169}, {"from": 119, "to": 50, "weight": 90.169}, {"from": 50, "to": 230, "weight": 128.2759}, {"from": 230, "to": 50, "weight": 128.2759}, {"from": 51, "to": 111, "weight": 115.943}, {"from": 111, "to": 51, "weight": 115.943}, {"from": 51, "to": 214, "weight": 86.5333}, {"from": 214, "to": 51, "weight": 86.5333}, {"from": 51, "to": 317, "weight": 150.79}, {"from": 317, "to": 51, "weight": 150.79}, {"from": 52, "to": 72, "weight": 201.7757}, {"from": 72, "to": 52, "weight": 201.7757}, {"from": 52, "to": 258, "weight": 65.1897}, {"from": 258, "to": 52, "weight": 65.1897}, {"from": 52, "to": 266, "weight": 80.3455}, {"from": 266, "to": 52, "weight": 80.3455}, {"from": 54, "to": 154, "weight": 90.544}, {"from": 154, "to": 54, "weight": 90.544}, {"from": 55, "to": 80, "weight": 128.5496}, {"from": 80, "to": 55, "weight": 128.5496}, {"from": 55, "to": 113, "weight": 86.9856}, {"from": 113, "to": 55, "weight": 86.9856}, {"from": 56, "to": 224, "weight": 83.9816}, {"from": 224, "to": 56, "weight": 83.9816}, {"from": 56, "to": 266, "weight": 70.954}, {"from": 266, "to": 56, "weight": 70.954}, {"from": 66, "to": 101, "weight": 85.7337}, {"from": 101, "to": 66, "weight": 85.7337}, {"from": 66, "to": 161, "weight": 119.4362}, {"from": 161, "to": 66, "weight": 119.4362}, {"from": 67, "to": 74, "weight": 110.69}, {"from": 74, "to": 67, "weight": 110.69}, {"from": 67, "to": 101, "weight": 101.756}, {"from": 101, "to": 67, "weight": 101.756}, {"from": 68, "to": 168, "weight": 90.9794}, {"from": 168, "to": 68, "weight": 90.9794}, {"from": 68, "to": 209, "weight": 80.4814}, {"from": 209, "to": 68, "weight": 80.4814}, {"from": 69, "to": 134, "weight": 102.0601}, {"from": 134, "to": 69, "weight": 102.0601}, {"from": 69, "to": 260, "weight": 113.4957}, {"from": 260, "to": 69, "weight": 113.4957}, {"from": 69, "to": 295, "weight": 128.3122}, {"from": 295, "to": 69, "weight": 128.3122}, {"from": 72, "to": 264, "weight": 82.6226}, {"from": 264, "to": 72, "weight": 82.6226}, {"from": 74, "to": 132, "weight": 299.013}, {"from": 132, "to": 74, "weight": 299.013}, {"from": 74, "to": 270, "weight": 97.4064}, {"from": 270, "to": 74, "weight": 97.4064}, {"from": 80, "to": 107, "weight": 180.0391}, {"from": 107, "to": 80, "weight": 180.0391}, {"from": 80, "to": 111, "weight": 115.1314}, {"from": 111, "to": 80, "weight": 115.1314}, {"from": 81, "to": 89, "weight": 175.7088}, {"from": 89, "to": 81, "weight": 175.7088}, {"from": 81, "to": 154, "weight": 104.214}, {"from": 154, "to": 81, "weight": 104.214}, {"from": 81, "to": 158, "weight": 150.5969}, {"from": 158, "to": 81, "weight": 150.5969}, {"from": 81, "to": 179, "weight": 152.0692}, {"from": 179, "to": 81, "weight": 152.0692}, {"from": 82, "to": 144, "weight": 168.003}, {"from": 144, "to": 82, "weight": 168.003}, {"from": 84, "to": 189, "weight": 127.3549}, {"from": 189, "to": 84, "weight": 127.3549}, {"from": 84, "to": 248, "weight": 124.0977}, {"from": 248, "to": 84, "weight": 124.0977}, {"from": 84, "to": 300, "weight": 82.1736}, {"from": 300, "to": 84, "weight": 82.1736}, {"from": 86, "to": 91, "weight": 268.2197}, {"from": 91, "to": 86, "weight": 268.2197}, {"from": 87, "to": 253, "weight": 90.824}, {"from": 253, "to": 87, "weight": 90.824}, {"from": 87, "to": 295, "weight": 109.5568}, {"from": 295, "to": 87, "weight": 109.5568}, {"from": 89, "to": 92, "weight": 85.7298}, {"from": 92, "to": 89, "weight": 85.7298}, {"from": 91, "to": 163, "weight": 99.0409}, {"from": 163, "to": 91, "weight": 99.0409}, {"from": 93, "to": 317, "weight": 122.5367}, {"from": 317, "to": 93, "weight": 122.5367}, {"from": 94, "to": 287, "weight": 137.7844}, {"from": 287, "to": 94, "weight": 137.7844}, {"from": 95, "to": 205, "weight": 114.5284}, {"from": 205, "to": 95, "weight": 114.5284}, {"from": 103, "to": 244, "weight": 100.1401}, {"from": 244, "to": 103, "weight": 100.1401}, {"from": 103, "to": 276, "weight": 90.061}, {"from": 276, "to": 103, "weight": 90.061}, {"from": 103, "to": 298, "weight": 90.7343}, {"from": 298, "to": 103, "weight": 90.7343}, {"from": 103, "to": 301, "weight": 116.9542}, {"from": 301, "to": 103, "weight": 116.9542}, {"from": 105, "to": 130, "weight": 139.262}, {"from": 130, "to": 105, "weight": 139.262}, {"from": 105, "to": 161, "weight": 173.0047}, {"from": 161, "to": 105, "weight": 173.0047}, {"from": 107, "to": 109, "weight": 175.172}, {"from": 109, "to": 107, "weight": 175.172}, {"from": 109, "to": 288, "weight": 112.4397}, {"from": 288, "to": 109, "weight": 112.4397}, {"from": 111, "to": 113, "weight": 193.5233}, {"from": 113, "to": 111, "weight": 193.5233}, {"from": 111, "to": 132, "weight": 153.0501}, {"from": 132, "to": 111, "weight": 153.0501}, {"from": 112, "to": 138, "weight": 96.7945}, {"from": 138, "to": 112, "weight": 96.7945}, {"from": 112, "to": 183, "weight": 88.411}, {"from": 183, "to": 112, "weight": 88.411}, {"from": 113, "to": 200, "weight": 94.4524}, {"from": 200, "to": 113, "weight": 94.4524}, {"from": 117, "to": 122, "weight": 101.5531}, {"from": 122, "to": 117, "weight": 101.5531}, {"from": 117, "to": 156, "weight": 108.5819}, {"from": 156, "to": 117, "weight": 108.5819}, {"from": 119, "to": 126, "weight": 86.5}, {"from": 126, "to": 119, "weight": 86.5}, {"from": 121, "to": 279, "weight": 115.8146}, {"from": 279, "to": 121, "weight": 115.8146}, {"from": 122, "to": 232, "weight": 134.8004}, {"from": 232, "to": 122, "weight": 134.8004}, {"from": 127, "to": 198, "weight": 126.3046}, {"from": 198, "to": 127, "weight": 126.3046}, {"from": 128, "to": 218, "weight": 186.5505}, {"from": 218, "to": 128, "weight": 186.5505}, {"from": 130, "to": 184, "weight": 104.2039}, {"from": 184, "to": 130, "weight": 104.2039}, {"from": 137, "to": 184, "weight": 116.5795}, {"from": 184, "to": 137, "weight": 116.5795}, {"from": 137, "to": 307, "weight": 83.5414}, {"from": 307, "to": 137, "weight": 83.5414}, {"from": 138, "to": 139, "weight": 97.2051}, {"from": 139, "to": 138, "weight": 97.2051}, {"from": 138, "to": 168, "weight": 89.2996}, {"from": 168, "to": 138, "weight": 89.2996}, {"from": 138, "to": 183, "weight": 88.6374}, {"from": 183, "to": 138, "weight": 88.6374}, {"from": 139, "to": 183, "weight": 80.2379}, {"from": 183, "to": 139, "weight": 80.2379}, {"from": 139, "to": 224, "weight": 107.9816}, {"from": 224, "to": 139, "weight": 107.9816}, {"from": 143, "to": 217, "weight": 100.6789}, {"from": 217, "to": 143, "weight": 100.6789}, {"from": 149, "to": 171, "weight": 143.3745}, {"from": 171, "to": 149, "weight": 143.3745}, {"from": 149, "to": 186, "weight": 151.7465}, {"from": 186, "to": 149, "weight": 151.7465}, {"from": 149, "to": 191, "weight": 99.0581}, {"from": 191, "to": 149, "weight": 99.0581}, {"from": 149, "to": 246, "weight": 136.0871}, {"from": 246, "to": 149, "weight": 136.0871}, {"from": 150, "to": 280, "weight": 80.6535}, {"from": 280, "to": 150, "weight": 80.6535}, {"from": 150, "to": 300, "weight": 90.5939}, {"from": 300, "to": 150, "weight": 90.5939}, {"from": 154, "to": 158, "weight": 144.2476}, {"from": 158, "to": 154, "weight": 144.2476}, {"from": 156, "to": 190, "weight": 114.7005}, {"from": 190, "to": 156, "weight": 114.7005}, {"from": 157, "to": 249, "weight": 97.2933}, {"from": 249, "to": 157, "weight": 97.2933}, {"from": 157, "to": 296, "weight": 81.3203}, {"from": 296, "to": 157, "weight": 81.3203}, {"from": 158, "to": 179, "weight": 148.6114}, {"from": 179, "to": 158, "weight": 148.6114}, {"from": 158, "to": 228, "weight": 149.3083}, {"from": 228, "to": 158, "weight": 149.3083}, {"from": 159, "to": 161, "weight": 154.0658}, {"from": 161, "to": 159, "weight": 154.0658}, {"from": 159, "to": 240, "weight": 137.99}, {"from": 240, "to": 159, "weight": 137.99}, {"from": 160, "to": 302, "weight": 138.0711}, {"from": 302, "to": 160, "weight": 138.0711}, {"from": 162, "to": 171, "weight": 135.9278}, {"from": 171, "to": 162, "weight": 135.9278}, {"from": 162, "to": 281, "weight": 120.6439}, {"from": 281, "to": 162, "weight": 120.6439}, {"from": 169, "to": 172, "weight": 117.5638}, {"from": 172, "to": 169, "weight": 117.5638}, {"from": 169, "to": 230, "weight": 114.6222}, {"from": 230, "to": 169, "weight": 114.6222}, {"from": 170, "to": 171, "weight": 87.0761}, {"from": 171, "to": 170, "weight": 87.0761}, {"from": 171, "to": 281, "weight": 125.7548}, {"from": 281, "to": 171, "weight": 125.7548}, {"from": 172, "to": 234, "weight": 129.0513}, {"from": 234, "to": 172, "weight": 129.0513}, {"from": 179, "to": 223, "weight": 69.4669}, {"from": 223, "to": 179, "weight": 69.4669}, {"from": 180, "to": 203, "weight": 112.8208}, {"from": 203, "to": 180, "weight": 112.8208}, {"from": 180, "to": 207, "weight": 116.8953}, {"from": 207, "to": 180, "weight": 116.8953}, {"from": 184, "to": 307, "weight": 136.1886}, {"from": 307, "to": 184, "weight": 136.1886}, {"from": 186, "to": 246, "weight": 104.3985}, {"from": 246, "to": 186, "weight": 104.3985}, {"from": 186, "to": 318, "weight": 93.3912}, {"from": 318, "to": 186, "weight": 93.3912}, {"from": 189, "to": 300, "weight": 136.9535}, {"from": 300, "to": 189, "weight": 136.9535}, {"from": 191, "to": 246, "weight": 125.0263}, {"from": 246, "to": 191, "weight": 125.0263}, {"from": 191, "to": 307, "weight": 124.763}, {"from": 307, "to": 191, "weight": 124.763}, {"from": 192, "to": 217, "weight": 165.7362}, {"from": 217, "to": 192, "weight": 165.7362}, {"from": 192, "to": 274, "weight": 149.5535}, {"from": 274, "to": 192, "weight": 149.5535}, {"from": 196, "to": 203, "weight": 160.7491}, {"from": 203, "to": 196, "weight": 160.7491}, {"from": 196, "to": 215, "weight": 124.6084}, {"from": 215, "to": 196, "weight": 124.6084}, {"from": 200, "to": 213, "weight": 122.3805}, {"from": 213, "to": 200, "weight": 122.3805}, {"from": 203, "to": 249, "weight": 95.0788}, {"from": 249, "to": 203, "weight": 95.0788}, {"from": 205, "to": 216, "weight": 102.103}, {"from": 216, "to": 205, "weight": 102.103}, {"from": 207, "to": 215, "weight": 98.4403}, {"from": 215, "to": 207, "weight": 98.4403}, {"from": 210, "to": 298, "weight": 141.5284}, {"from": 298, "to": 210, "weight": 141.5284}, {"from": 217, "to": 274, "weight": 81.5552}, {"from": 274, "to": 217, "weight": 81.5552}, {"from": 223, "to": 228, "weight": 140.074}, {"from": 228, "to": 223, "weight": 140.074}, {"from": 224, "to": 240, "weight": 113.4912}, {"from": 240, "to": 224, "weight": 113.4912}, {"from": 232, "to": 276, "weight": 95.5071}, {"from": 276, "to": 232, "weight": 95.5071}, {"from": 235, "to": 244, "weight": 105.7888}, {"from": 244, "to": 235, "weight": 105.7888}, {"from": 235, "to": 276, "weight": 97.1848}, {"from": 276, "to": 235, "weight": 97.1848}, {"from": 246, "to": 307, "weight": 97.9167}, {"from": 307, "to": 246, "weight": 97.9167}, {"from": 248, "to": 300, "weight": 147.1316}, {"from": 300, "to": 248, "weight": 147.1316}, {"from": 253, "to": 259, "weight": 125.3321}, {"from": 259, "to": 253, "weight": 125.3321}, {"from": 253, "to": 260, "weight": 100.8588}, {"from": 260, "to": 253, "weight": 100.8588}, {"from": 259, "to": 283, "weight": 93.6402}, {"from": 283, "to": 259, "weight": 93.6402}, {"from": 260, "to": 283, "weight": 82.3847}, {"from": 283, "to": 260, "weight": 82.3847}, {"from": 105, "to": 217, "weight": 79.6321}, {"from": 217, "to": 105, "weight": 79.6321}, {"from": 137, "to": 143, "weight": 122.5491}, {"from": 143, "to": 137, "weight": 122.5491}, {"from": 145, "to": 228, "weight": 87.0129}, {"from": 228, "to": 145, "weight": 87.0129}, {"from": 207, "to": 323, "weight": 83.291}, {"from": 323, "to": 207, "weight": 83.291}, {"from": 210, "to": 319, "weight": 105.6611}, {"from": 319, "to": 210, "weight": 105.6611}, {"from": 13, "to": 19, "weight": 117.0118}, {"from": 19, "to": 13, "weight": 117.0118}, {"from": 163, "to": 12, "weight": 143.3538}, {"from": 12, "to": 163, "weight": 143.3538}, {"from": 286, "to": 91, "weight": 416.7925}, {"from": 91, "to": 286, "weight": 416.7925}, {"from": 134, "to": 86, "weight": 196.8008}, {"from": 86, "to": 134, "weight": 196.8008}, {"from": 286, "to": 134, "weight": 319.5579}, {"from": 134, "to": 286, "weight": 319.5579}, {"from": 118, "to": 264, "weight": 358.3564}, {"from": 264, "to": 118, "weight": 358.3564}, {"from": 35, "to": 258, "weight": 210.7955}, {"from": 258, "to": 35, "weight": 210.7955}, {"from": 35, "to": 118, "weight": 170.5313}, {"from": 118, "to": 35, "weight": 170.5313}, {"from": 35, "to": 140, "weight": 211.2227}, {"from": 140, "to": 35, "weight": 211.2227}, {"from": 299, "to": 127, "weight": 263.838}, {"from": 127, "to": 299, "weight": 263.838}, {"from": 57, "to": 173, "weight": 527.6859}, {"from": 173, "to": 57, "weight": 527.6859}, {"from": 176, "to": 173, "weight": 287.6755}, {"from": 173, "to": 176, "weight": 287.6755}, {"from": 97, "to": 57, "weight": 301.5018}, {"from": 57, "to": 97, "weight": 301.5018}, {"from": 88, "to": 79, "weight": 311.0486}, {"from": 79, "to": 88, "weight": 311.0486}, {"from": 88, "to": 97, "weight": 298.1706}, {"from": 97, "to": 88, "weight": 298.1706}, {"from": 287, "to": 331, "weight": 938.0601}, {"from": 331, "to": 287, "weight": 938.0601}, {"from": 97, "to": 331, "weight": 320.2105}, {"from": 331, "to": 97, "weight": 320.2105}, {"from": 287, "to": 176, "weight": 175.7093}, {"from": 176, "to": 287, "weight": 175.7093}, {"from": 6, "to": 287, "weight": 297.1836}, {"from": 287, "to": 6, "weight": 297.1836}, {"from": 106, "to": 299, "weight": 98.4988}, {"from": 299, "to": 106, "weight": 98.4988}, {"from": 248, "to": 106, "weight": 221.3775}, {"from": 106, "to": 248, "weight": 221.3775}, {"from": 37, "to": 63, "weight": 138.1918}, {"from": 63, "to": 37, "weight": 138.1918}, {"from": 42, "to": 126, "weight": 114.5044}, {"from": 126, "to": 42, "weight": 114.5044}, {"from": 126, "to": 110, "weight": 220.2981}, {"from": 110, "to": 126, "weight": 220.2981}, {"from": 110, "to": 95, "weight": 221.1119}, {"from": 95, "to": 110, "weight": 221.1119}, {"from": 14, "to": 205, "weight": 174.1407}, {"from": 205, "to": 14, "weight": 174.1407}, {"from": 205, "to": 160, "weight": 296.801}, {"from": 160, "to": 205, "weight": 296.801}, {"from": 160, "to": 95, "weight": 241.7059}, {"from": 95, "to": 160, "weight": 241.7059}, {"from": 302, "to": 332, "weight": 91.0152}, {"from": 332, "to": 302, "weight": 91.0152}, {"from": 332, "to": 43, "weight": 137.7722}, {"from": 43, "to": 332, "weight": 137.7722}, {"from": 153, "to": 332, "weight": 99.5193}, {"from": 332, "to": 153, "weight": 99.5193}, {"from": 43, "to": 302, "weight": 190.4207}, {"from": 302, "to": 43, "weight": 190.4207}, {"from": 15, "to": 198, "weight": 171.1026}, {"from": 198, "to": 15, "weight": 171.1026}, {"from": 125, "to": 2, "weight": 257.9393}, {"from": 2, "to": 125, "weight": 257.9393}, {"from": 2, "to": 0, "weight": 267.403}, {"from": 0, "to": 2, "weight": 267.403}, {"from": 125, "to": 0, "weight": 207.0175}, {"from": 0, "to": 125, "weight": 207.0175}, {"from": 5, "to": 23, "weight": 232.3731}, {"from": 23, "to": 5, "weight": 232.3731}, {"from": 312, "to": 5, "weight": 260.3059}, {"from": 5, "to": 312, "weight": 260.3059}, {"from": 312, "to": 23, "weight": 278.0789}, {"from": 23, "to": 312, "weight": 278.0789}, {"from": 58, "to": 312, "weight": 484.2811}, {"from": 312, "to": 58, "weight": 484.2811}, {"from": 58, "to": 23, "weight": 285.7218}, {"from": 23, "to": 58, "weight": 285.7218}, {"from": 58, "to": 234, "weight": 231.6918}, {"from": 234, "to": 58, "weight": 231.6918}, {"from": 234, "to": 23, "weight": 403.9439}, {"from": 23, "to": 234, "weight": 403.9439}, {"from": 216, "to": 7, "weight": 111.5495}, {"from": 7, "to": 216, "weight": 111.5495}, {"from": 92, "to": 216, "weight": 137.1287}, {"from": 216, "to": 92, "weight": 137.1287}, {"from": 7, "to": 205, "weight": 197.7784}, {"from": 205, "to": 7, "weight": 197.7784}, {"from": 14, "to": 7, "weight": 162.657}, {"from": 7, "to": 14, "weight": 162.657}, {"from": 36, "to": 205, "weight": 265.9115}, {"from": 205, "to": 36, "weight": 265.9115}, {"from": 287, "to": 4, "weight": 299.2241}, {"from": 4, "to": 287, "weight": 299.2241}, {"from": 115, "to": 4, "weight": 391.1411}, {"from": 4, "to": 115, "weight": 391.1411}, {"from": 115, "to": 9, "weight": 239.2384}, {"from": 9, "to": 115, "weight": 239.2384}, {"from": 109, "to": 46, "weight": 129.1733}, {"from": 46, "to": 109, "weight": 129.1733}, {"from": 94, "to": 46, "weight": 357.5458}, {"from": 46, "to": 94, "weight": 357.5458}, {"from": 232, "to": 116, "weight": 213.9843}, {"from": 116, "to": 232, "weight": 213.9843}, {"from": 157, "to": 116, "weight": 168.3138}, {"from": 116, "to": 157, "weight": 168.3138}, {"from": 128, "to": 116, "weight": 134.952}, {"from": 116, "to": 128, "weight": 134.952}, {"from": 116, "to": 122, "weight": 336.6056}, {"from": 122, "to": 116, "weight": 336.6056}, {"from": 9, "to": 122, "weight": 281.9809}, {"from": 122, "to": 9, "weight": 281.9809}, {"from": 287, "to": 122, "weight": 452.694}, {"from": 122, "to": 287, "weight": 452.694}, {"from": 214, "to": 93, "weight": 170.6238}, {"from": 93, "to": 214, "weight": 170.6238}, {"from": 264, "to": 214, "weight": 243.7853}, {"from": 214, "to": 264, "weight": 243.7853}, {"from": 82, "to": 264, "weight": 150.2415}, {"from": 264, "to": 82, "weight": 150.2415}, {"from": 41, "to": 144, "weight": 169.7181}, {"from": 144, "to": 41, "weight": 169.7181}, {"from": 270, "to": 144, "weight": 367.3462}, {"from": 144, "to": 270, "weight": 367.3462}, {"from": 240, "to": 32, "weight": 191.1472}, {"from": 32, "to": 240, "weight": 191.1472}, {"from": 295, "to": 140, "weight": 189.8932}, {"from": 140, "to": 295, "weight": 189.8932}, {"from": 93, "to": 29, "weight": 363.698}, {"from": 29, "to": 93, "weight": 363.698}, {"from": 218, "to": 93, "weight": 71.8084}, {"from": 93, "to": 218, "weight": 71.8084}, {"from": 218, "to": 29, "weight": 357.3007}, {"from": 29, "to": 218, "weight": 357.3007}, {"from": 317, "to": 29, "weight": 257.6141}, {"from": 29, "to": 317, "weight": 257.6141}, {"from": 326, "to": 153, "weight": 199.395}, {"from": 153, "to": 326, "weight": 199.395}, {"from": 153, "to": 85, "weight": 183.4897}, {"from": 85, "to": 153, "weight": 183.4897}, {"from": 148, "to": 153, "weight": 196.5816}, {"from": 153, "to": 148, "weight": 196.5816}, {"from": 10, "to": 15, "weight": 322.563}, {"from": 15, "to": 10, "weight": 322.563}, {"from": 304, "to": 63, "weight": 141.0893}, {"from": 63, "to": 304, "weight": 141.0893}, {"from": 333, "to": 63, "weight": 213.693}, {"from": 63, "to": 333, "weight": 213.693}, {"from": 219, "to": 333, "weight": 275.9044}, {"from": 333, "to": 219, "weight": 275.9044}, {"from": 324, "to": 333, "weight": 171.5116}, {"from": 333, "to": 324, "weight": 171.5116}, {"from": 117, "to": 324, "weight": 208.3942}, {"from": 324, "to": 117, "weight": 208.3942}, {"from": 333, "to": 190, "weight": 154.9283}, {"from": 190, "to": 333, "weight": 154.9283}, {"from": 219, "to": 287, "weight": 273.9579}, {"from": 287, "to": 219, "weight": 273.9579}], "segment_looks": {"T": [], "CT": []}}